orgassist/__init__.py
orgassist/assistant.py
orgassist/config.py
orgassist/config.tmpl.yml
orgassist/templates.py
orgassist/tests.py
orgassist/assistant/__init__.py
orgassist/assistant/api.py
orgassist/assistant/assistant.py
orgassist/assistant/command.py
orgassist/bots/__init__.py
orgassist/bots/api.py
orgassist/bots/xmpp_bot.py
orgassist/calendar/__init__.py
orgassist/calendar/calendar.py
orgassist/calendar/event.py
orgassist/calendar/event_date.py
orgassist/calendar/tests.py
orgassist/config/__init__.py
orgassist/config/config.py
orgassist/config/tests.py
orgassist/helpers/__init__.py
orgassist/helpers/language.py
orgassist/helpers/templates.py
orgassist/helpers/time.py
orgassist/plugins/__init__.py
orgassist/plugins/core/__init__.py
orgassist/plugins/core/calendar.py
orgassist/plugins/core/templates/__init__.py
orgassist/plugins/core/templates/agenda.txt.j2
orgassist/plugins/core/templates/notice.txt.j2
orgassist/plugins/exch/__init__.py
orgassist/plugins/exch/plugin.py
orgassist/plugins/org/__init__.py
orgassist/plugins/org/helpers.py
orgassist/plugins/org/plugin.py
orgassist/plugins/org/tests.py
orgassist/plugins/org/orgnode/__init__.py
orgassist/plugins/org/orgnode/orgnode.py
orgassist/plugins/org/orgnode/orgreports.py
orgassist/plugins/org/templates/__init__.py
orgassist/plugins/org/templates/new_note.txt.j2
orgassist-0.4.0.data/scripts/assist.py
orgassist-0.4.0.dist-info/METADATA
orgassist-0.4.0.dist-info/RECORD
orgassist-0.4.0.dist-info/WHEEL
orgassist-0.4.0.dist-info/top_level.txt
