Metadata-Version: 2.1
Name: orgassist
Version: 0.4.0
Summary: Assistant who handles your appointments, tasks and note-taking when you're away from your computer
Home-page: https://github.com/blaa/orgassist
Author: Tomasz bla Fortuna
Author-email: bla@thera.be
License: MIT
Keywords: org-mode emacs bot xmpp planner
Platform: UNKNOWN
Classifier: Development Status :: 3 - Alpha
Classifier: License :: OSI Approved :: MIT License
Classifier: Topic :: Communications :: Chat
Classifier: Topic :: Internet :: XMPP
Classifier: Topic :: Office/Business :: Scheduling
Classifier: Topic :: Text Editors :: Emacs
Provides-Extra: exchange_plugin
Requires-Dist: Jinja2 (>=2.10)
Requires-Dist: PyYAML (==3.12)
Requires-Dist: dnspython (==1.15.0)
Requires-Dist: pytz (>=2018.4)
Requires-Dist: schedule (>=0.5.0)
Requires-Dist: sleekxmpp (==1.3.3)
Provides-Extra: exchange_plugin
Requires-Dist: pyexchange (==0.6); extra == 'exchange_plugin'
